Metadata-Version: 1.0
Name: mmal-pandas
Version: 0.0.2
Summary: Meteorological Middleware Application Layer pandas bindings
Home-page: https://github.com/hodgesds/mmbal-pandas
Author: Daniel Hodges
Author-email: hodges.daniel.scott@gmail.com
License: UNKNOWN
Platform: UNKNOWN
